whassup/__init__.py
whassup/admin.py
whassup/apps.py
whassup/face_recognition_service.py
whassup/models.py
whassup/tests.py
whassup/urls.py
whassup/views.py
whassup/weather_service.py
whassup/migrations/0001_initial.py
whassup/migrations/__init__.py
whassup_V11.1.2-11.1.2.dist-info/METADATA
whassup_V11.1.2-11.1.2.dist-info/WHEEL
whassup_V11.1.2-11.1.2.dist-info/entry_points.txt
whassup_V11.1.2-11.1.2.dist-info/top_level.txt
whassup_V11.1.2-11.1.2.dist-info/RECORD
